polish_py_payments/__init__.py
polish_py_payments/hotpay/__init__.py
polish_py_payments/hotpay/exceptions.py
polish_py_payments/hotpay/main.py
polish_py_payments/lvlup/__init__.py
polish_py_payments/lvlup/main.py
polish_py_payments/microsms/__init__.py
polish_py_payments/microsms/exceptions.py
polish_py_payments/microsms/main.py
polish_py_payments/microsms/utils.py
polish_py_payments-1.0.0.dist-info/LICENSE
polish_py_payments-1.0.0.dist-info/METADATA
polish_py_payments-1.0.0.dist-info/WHEEL
polish_py_payments-1.0.0.dist-info/top_level.txt
polish_py_payments-1.0.0.dist-info/RECORD
