Metadata-Version: 2.1
Name: polish-py-payments
Version: 1.0.0
Summary: Polish payment providers in python
Home-page: https://github.com/ivall/polish-py-payments
Author: ivall
License: MIT
Keywords: polish payments,payments,payment provider
Platform: UNKNOWN
Classifier: Intended Audience :: Developers
Classifier: License :: OSI Approved :: MIT License
Classifier: Programming Language :: Python :: 3
Requires-Python: >=3.6, <4
Requires-Dist: requests
